[
  {
    "name": "Free Unequip",
    "start": "2020-04-23 03:00:00Z",
    "end": "2020-04-26 15:00:00Z"
  },
  {
    "name": "Free Unequip",
    "start": "2020-04-30 03:00:00Z",
    "end": "2020-05-03 15:00:00Z"
  },
  {
    "name": "+30% Gold/+50% Hunt Mats",
    "start": "2020-04-30 03:00:00Z",
    "end": "2020-05-04 03:00:00Z"
  },
  {
    "name": "Double Altar Rune Drop",
    "start": "2020-05-04 03:00:00Z",
    "end": "2020-05-07 03:00:00Z"
  },
  {
    "name": "+50% AP/+30% EXP",
    "start": "2020-05-07 03:00:00Z",
    "end": "2020-05-10 03:00:00Z"
  }
]